{"dataURL":"file:\/\/\/Users\/tianxiangsong\/Library\/Mobile%20Documents\/com~apple~CloudDocs\/Y3S2\/FYP\/Data\/Data3\/Train\/","id":"E089EDEC-DF64-4191-98E4-E6B9E9E75EE7","createdDate":"2023-03-01T11:13:39Z","title":"Train","modifiedDate":"2023-03-01T11:14:35Z","preferredFilename":"Train","version":"1.0","dataResult":{"itemsCount":858,"createdDate":"2023-03-01T11:13:39Z","dataURL":"file:\/\/\/Users\/tianxiangsong\/Library\/Mobile%20Documents\/com~apple~CloudDocs\/Y3S2\/FYP\/Data\/Data3\/Train\/","dataSourceID":"E089EDEC-DF64-4191-98E4-E6B9E9E75EE7","classesCount":2,"dataAnalysis":{"summary":{"sampleCount":858,"classCount":2,"canUseValidation":1},"issues":[{"description":"2 classes found, including Finished, Unfinished","severity":"debug"},{"description":"858 images found, automatically creating validation set","severity":"good"},{"description":"Smallest class is \"Unfinished\" with 425 images","severity":"debug"},{"description":"Largest class is \"Finished\" with 433 images","severity":"debug"}],"classifierAnalysis":{"labelStats":{"Unfinished":425,"Finished":433}}}},"activityEntities":["dataSourceCreated",[{"id":"5811A166-FD50-416D-B37B-A98E83D5E783","title":"Data Source Created","createdDate":"2023-03-01T11:13:39Z","event":"dataSourceCreated","subtitle":"Train"}],"dataSourceMetrics",[{"id":"4962B67E-4BE3-47DF-AE55-BD9B085B7F85","title":"Data Summary","createdDate":"2023-03-01T11:14:35Z","event":"dataSourceMetrics","subtitle":"2 Classes, 858 Items"}],"dataSourceTrainingStarted",[{"id":"78C4F9BA-5278-461F-88C0-7491F8E1E706","title":"Used By","createdDate":"2023-03-01T11:14:35Z","event":"dataSourceTrainingStarted","subtitle":"LEGOStepClassifier 8"}]],"pathType":0,"experimentIDs":["26162053-D58B-43D5-BC99-2B6541F850D4"]}